phys2bids/__init__.py
phys2bids/_version.py
phys2bids/bids.py
phys2bids/due.py
phys2bids/io.py
phys2bids/phys2bids.py
phys2bids/physio_obj.py
phys2bids/slice4phys.py
phys2bids/utils.py
phys2bids/viz.py
phys2bids/cli/__init__.py
phys2bids/cli/run.py
phys2bids/heuristics/heur_euskalibur.py
phys2bids/heuristics/heur_test_acq.py
phys2bids/heuristics/heur_test_multifreq.py
phys2bids/heuristics/heur_tutorial.py
phys2bids/heuristics/participant.yml
phys2bids/tests/__init__.py
phys2bids/tests/conftest.py
phys2bids/tests/test_bids.py
phys2bids/tests/test_integration.py
phys2bids/tests/test_io.py
phys2bids/tests/test_phys2bids.py
phys2bids/tests/test_physio_obj.py
phys2bids/tests/test_utils.py
phys2bids/tests/test_viz.py
phys2bids/tests/data/README.md
phys2bids/tests/data/tutorial_file_INFO.json
phys2bids-2.10.0.dist-info/LICENSE
phys2bids-2.10.0.dist-info/METADATA
phys2bids-2.10.0.dist-info/WHEEL
phys2bids-2.10.0.dist-info/entry_points.txt
phys2bids-2.10.0.dist-info/top_level.txt
phys2bids-2.10.0.dist-info/RECORD
