Metadata-Version: 2.1
Name: phys2bids
Version: 2.10.0
Summary: Python library to convert physiological data files into BIDS format
Home-page: https://github.com/physiopy/phys2bids
Author: phys2bids developers
Maintainer: Stefano Moia
Maintainer-email: s.moia@bcbl.eu
License: Apache-2.0
Download-URL: https://github.com/physiopy/phys2bids
Platform: OS Independent
Classifier: Development Status :: 5 - Production/Stable
Classifier: Intended Audience :: Science/Research
Classifier: License :: OSI Approved :: Apache Software License
Classifier: Programming Language :: Python :: 3.6
Classifier: Programming Language :: Python :: 3.7
Classifier: Programming Language :: Python :: 3.8
Classifier: Programming Language :: Python :: 3.9
Classifier: Programming Language :: Python :: 3.10
Provides: phys2bids
Requires-Python: >=3.6.1
Requires-Dist: numpy (<1.24,>=1.10)
Requires-Dist: matplotlib (!=3.3.0rc1,>=3.1.1)
Requires-Dist: PyYAML (>=5.1)
Provides-Extra: acq
Requires-Dist: bioread (>=1.0.5) ; extra == 'acq'
Provides-Extra: all
Requires-Dist: sphinx (>=2.0) ; extra == 'all'
Requires-Dist: sphinx-argparse ; extra == 'all'
Requires-Dist: sphinx-rtd-theme ; extra == 'all'
Requires-Dist: duecredit ; extra == 'all'
Requires-Dist: bioread (>=1.0.5) ; extra == 'all'
Requires-Dist: pymatreader (>=0.0.24) ; extra == 'all'
Requires-Dist: flake8 (>=4.0) ; extra == 'all'
Requires-Dist: black ; extra == 'all'
Requires-Dist: isort (<6.0.0) ; extra == 'all'
Requires-Dist: pydocstyle ; extra == 'all'
Requires-Dist: codespell ; extra == 'all'
Requires-Dist: pytest (>=5.3) ; extra == 'all'
Requires-Dist: pytest-cov ; extra == 'all'
Requires-Dist: coverage ; extra == 'all'
Requires-Dist: sonpy (>=1.7.5) ; (python_version == "3.7.*,3.8.*,3.9.*") and extra == 'all'
Provides-Extra: doc
Requires-Dist: sphinx (>=2.0) ; extra == 'doc'
Requires-Dist: sphinx-argparse ; extra == 'doc'
Requires-Dist: sphinx-rtd-theme ; extra == 'doc'
Provides-Extra: duecredit
Requires-Dist: duecredit ; extra == 'duecredit'
Provides-Extra: interfaces
Requires-Dist: bioread (>=1.0.5) ; extra == 'interfaces'
Requires-Dist: pymatreader (>=0.0.24) ; extra == 'interfaces'
Requires-Dist: sonpy (>=1.7.5) ; (python_version == "3.7.*,3.8.*,3.9.*") and extra == 'interfaces'
Provides-Extra: mat
Requires-Dist: pymatreader (>=0.0.24) ; extra == 'mat'
Provides-Extra: spike2
Requires-Dist: sonpy (>=1.7.5) ; (python_version == "3.7.*,3.8.*,3.9.*") and extra == 'spike2'
Provides-Extra: style
Requires-Dist: flake8 (>=4.0) ; extra == 'style'
Requires-Dist: black ; extra == 'style'
Requires-Dist: isort (<6.0.0) ; extra == 'style'
Requires-Dist: pydocstyle ; extra == 'style'
Requires-Dist: codespell ; extra == 'style'
Provides-Extra: test
Requires-Dist: pytest (>=5.3) ; extra == 'test'
Requires-Dist: pytest-cov ; extra == 'test'
Requires-Dist: coverage ; extra == 'test'
Requires-Dist: bioread (>=1.0.5) ; extra == 'test'
Requires-Dist: pymatreader (>=0.0.24) ; extra == 'test'
Requires-Dist: flake8 (>=4.0) ; extra == 'test'
Requires-Dist: black ; extra == 'test'
Requires-Dist: isort (<6.0.0) ; extra == 'test'
Requires-Dist: pydocstyle ; extra == 'test'
Requires-Dist: codespell ; extra == 'test'
Requires-Dist: sonpy (>=1.7.5) ; (python_version == "3.7.*,3.8.*,3.9.*") and extra == 'test'
